langchain_vedb/__init__.py
langchain_vedb/py.typed
langchain_vedb/vectorstores.py
langchain_vedb-0.1.3.dist-info/LICENSE
langchain_vedb-0.1.3.dist-info/METADATA
langchain_vedb-0.1.3.dist-info/WHEEL
langchain_vedb-0.1.3.dist-info/RECORD
