Metadata-Version: 2.3
Name: langchain-vedb
Version: 0.1.3
Summary: An integration package connecting VeDB and LangChain
License: MIT
Requires-Python: >=3.9,<4.0
Classifier: License :: OSI Approved :: MIT License
Classifier: Programming Language :: Python :: 3
Classifier: Programming Language :: Python :: 3.9
Classifier: Programming Language :: Python :: 3.10
Classifier: Programming Language :: Python :: 3.11
Classifier: Programming Language :: Python :: 3.12
Classifier: Programming Language :: Python :: 3.13
Requires-Dist: langchain-core (>=0.3.15,<0.4.0)
Requires-Dist: langchain-openai (>=0.3.25,<0.4.0)
Requires-Dist: mysql-connector-python (>=9.3.0,<10.0.0)
Requires-Dist: pymysql (>=1.1.1,<2.0.0)
Requires-Dist: vedbsearch (>=0.1.1,<0.2.0)
Project-URL: Repository, https://github.com/langchain-ai/langchain
Project-URL: Release Notes, https://github.com/yangsiyi1412ethan/langchain-vedb/releases
Project-URL: Source Code, https://github.com/yangsiyi1412ethan/langchain-vedb
